tswrangler/__init__.py
tswrangler/wrangler.py
tswrangler/tests/__init__.py
tswrangler/tests/conftest.py
tswrangler/tests/test_wrangler.py
tswrangler-0.0.1.dist-info/LICENSE.md
tswrangler-0.0.1.dist-info/METADATA
tswrangler-0.0.1.dist-info/WHEEL
tswrangler-0.0.1.dist-info/top_level.txt
tswrangler-0.0.1.dist-info/RECORD
