Metadata-Version: 2.1
Name: tswrangler
Version: 0.0.1
Summary: A small package to help wrangling pandas time series dataframes.
Home-page: https://github.com/kris7ian/tswrangler
Author: Kristian Arve
Author-email: kr.arve@gmail.com
License: UNKNOWN
Platform: UNKNOWN
Classifier: Programming Language :: Python :: 3
Classifier: License :: OSI Approved :: MIT License
Classifier: Operating System :: OS Independent
Requires-Python: >=3.6
